PooledDBhelper/DBhelper.py
PooledDBhelper/__init__.py
PooledDBhelper-1.0.0.dist-info/METADATA
PooledDBhelper-1.0.0.dist-info/WHEEL
PooledDBhelper-1.0.0.dist-info/top_level.txt
PooledDBhelper-1.0.0.dist-info/RECORD
