Metadata-Version: 2.1
Name: PooledDBhelper
Version: 1.0.0
Summary: A database tool
Home-page: UNKNOWN
Author: Cyprus0126
Author-email: 2459231463@qq.com
License: MIT
Keywords: PooledDBhelper
Platform: UNKNOWN
Requires-Dist: pymysql
Requires-Dist: dbutils
